odoo/addons/stock_putaway_product_template/README.rst
odoo/addons/stock_putaway_product_template/__init__.py
odoo/addons/stock_putaway_product_template/__manifest__.py
odoo/addons/stock_putaway_product_template/i18n/es.po
odoo/addons/stock_putaway_product_template/i18n/stock_putaway_product_template.pot
odoo/addons/stock_putaway_product_template/models/__init__.py
odoo/addons/stock_putaway_product_template/models/product.py
odoo/addons/stock_putaway_product_template/models/stock_location.py
odoo/addons/stock_putaway_product_template/models/stock_putaway_rule.py
odoo/addons/stock_putaway_product_template/readme/CONTRIBUTORS.rst
odoo/addons/stock_putaway_product_template/readme/DESCRIPTION.rst
odoo/addons/stock_putaway_product_template/readme/USAGE.rst
odoo/addons/stock_putaway_product_template/static/description/icon.png
odoo/addons/stock_putaway_product_template/static/description/index.html
odoo/addons/stock_putaway_product_template/tests/__init__.py
odoo/addons/stock_putaway_product_template/tests/test_stock_putaway_rule.py
odoo/addons/stock_putaway_product_template/views/stock_putaway_rule_views.xml
odoo14_addon_stock_putaway_product_template-14.0.1.1.0.dist-info/METADATA
odoo14_addon_stock_putaway_product_template-14.0.1.1.0.dist-info/WHEEL
odoo14_addon_stock_putaway_product_template-14.0.1.1.0.dist-info/top_level.txt
odoo14_addon_stock_putaway_product_template-14.0.1.1.0.dist-info/RECORD
